contextvars_extras/__init__.py
contextvars_extras/context_management.py
contextvars_extras/context_var_descriptor.py
contextvars_extras/context_var_ext.py
contextvars_extras/context_var_ext.pyi
contextvars_extras/context_vars_registry.py
contextvars_extras/integrations/__init__.py
contextvars_extras/integrations/flask.py
contextvars_extras/integrations/wsgi.py
contextvars_extras/internal_utils.py
contextvars_extras-0.7.0.dist-info/LICENSE
contextvars_extras-0.7.0.dist-info/METADATA
contextvars_extras-0.7.0.dist-info/WHEEL
contextvars_extras-0.7.0.dist-info/RECORD
