Metadata-Version: 2.1
Name: contextvars-extras
Version: 0.7.0
Summary: This package is not maintained anymore. Please switch to 'contextvars-registry'.
Home-page: https://github.com/vdmit11/contextvars-registry
License: MIT
Keywords: contextvars,context,async,threading,gevent
Author: Dmitry Vasilyanov
Author-email: vdmit11@gmail.com
Requires-Python: >=3.7.1,<4.0.0
Classifier: Development Status :: 4 - Beta
Classifier: Intended Audience :: Developers
Classifier: License :: OSI Approved :: MIT License
Classifier: Programming Language :: Python
Classifier: Programming Language :: Python :: 3
Classifier: Programming Language :: Python :: 3.8
Classifier: Programming Language :: Python :: 3.9
Classifier: Programming Language :: Python :: 3.10
Classifier: Programming Language :: Python :: 3.11
Classifier: Programming Language :: Python :: 3.12
Classifier: Programming Language :: Python :: 3.7
Classifier: Topic :: Software Development :: Libraries
Classifier: Topic :: Software Development :: Libraries :: Python Modules
Requires-Dist: sentinel-value (>=1.0.0,<2.0.0)
Project-URL: Documentation, https://contextvars-registry.readthedocs.io
Project-URL: Repository, https://github.com/vdmit11/contextvars-registry
